emissor-0.0.dev7-py3.13-nspkg.pth
emissor/persistence/__init__.py
emissor/persistence/persistence.py
emissor/processing/__init__.py
emissor/processing/__main__.py
emissor/processing/api.py
emissor/processing/processing.py
emissor/processing/util.py
emissor/representation/__init__.py
emissor/representation/annotation.py
emissor/representation/container.py
emissor/representation/entity.py
emissor/representation/ldschema.py
emissor/representation/scenario.py
emissor/representation/util.py
emissor-0.0.dev7.data/data/VERSION/VERSION
emissor-0.0.dev7.dist-info/licenses/LICENSE
emissor-0.0.dev7.dist-info/METADATA
emissor-0.0.dev7.dist-info/WHEEL
emissor-0.0.dev7.dist-info/namespace_packages.txt
emissor-0.0.dev7.dist-info/top_level.txt
emissor-0.0.dev7.dist-info/RECORD
