Metadata-Version: 2.4
Name: emissor
Version: 0.0.dev7
Summary: Representation of multi-modal datasets
Home-page: https://github.com/cltl/EMISSOR
Author: CLTL
Author-email: piek.vossen@vu.nl
Classifier: Programming Language :: Python :: 3
Classifier: License :: OSI Approved :: MIT License
Classifier: Operating System :: OS Independent
Requires-Python: >=3.7
License-File: LICENSE
Requires-Dist: numpy
Requires-Dist: marshmallow
Requires-Dist: marshmallow-dataclass
Requires-Dist: marshmallow-enum
Requires-Dist: marshmallow-union
Requires-Dist: rdflib
Requires-Dist: simplejson
Requires-Dist: typeguard
Provides-Extra: processing
Requires-Dist: joblib; extra == "processing"
Requires-Dist: tqdm; extra == "processing"
Requires-Dist: scikit-learn; extra == "processing"
Dynamic: author
Dynamic: author-email
Dynamic: classifier
Dynamic: description
Dynamic: description-content-type
Dynamic: home-page
Dynamic: license-file
Dynamic: provides-extra
Dynamic: requires-dist
Dynamic: requires-python
Dynamic: summary
